CHANGES.txt
MANIFEST.in
README.md
setup.cfg
setup.py
py_oneliner/__init__.py
py_oneliner/one_liner.py
py_oneliner.egg-info/PKG-INFO
py_oneliner.egg-info/SOURCES.txt
py_oneliner.egg-info/dependency_links.txt
py_oneliner.egg-info/requires.txt
py_oneliner.egg-info/top_level.txt