Metadata-Version: 2.1
Name: py-oneliner
Version: 0.0.1
Summary: Dynamic print statements for Python Projects
Home-page: https://github.com/fuzailpalnak/py_oneliner
Author: Fuzail Palnak
Author-email: fuzailpalnak@gmail.com
License: UNKNOWN
Keywords: Python,Print,OneLine Print
Platform: UNKNOWN
Classifier: Programming Language :: Python :: 3
Classifier: License :: OSI Approved :: MIT License
Classifier: Operating System :: OS Independent
Requires-Python: ~=3.6
